rply/__init__.py
rply/errors.py
rply/grammar.py
rply/lexer.py
rply/lexergenerator.py
rply/parser.py
rply/parsergenerator.py
rply/token.py
rply/utils.py
rply-0.7.8.dist-info/LICENSE
rply-0.7.8.dist-info/METADATA
rply-0.7.8.dist-info/WHEEL
rply-0.7.8.dist-info/top_level.txt
rply-0.7.8.dist-info/RECORD
