Metadata-Version: 1.0
Name: rply
Version: 0.7.8
Summary: A pure Python Lex/Yacc that works with RPython
Home-page: UNKNOWN
Author: Alex Gaynor
Author-email: alex.gaynor@gmail.com
License: BSD 3-Clause License
Platform: UNKNOWN
